TurboCLI/__init__.py
TurboCLI/_cli.py
TurboCLI/_core.py
tests/__init__.py
tests/test_hex.py
tests/test_hex37.py
turbocli-0.2.2.dist-info/LICENSE
turbocli-0.2.2.dist-info/METADATA
turbocli-0.2.2.dist-info/WHEEL
turbocli-0.2.2.dist-info/top_level.txt
turbocli-0.2.2.dist-info/RECORD
